Project/Monocycle/header.vh
`ifndef Macros_header
`define Macros_header
// Basics
`define BYTE_SIZE       1
`define WORD_SIZE       4

/////////////// Global stuff

// Virtual and Physical memory
`define VIRT_ADDR_WIDTH 32
`define PHY_ADDR_WIDTH  20
`define PAGE_SIZE_BITS  12 // 4 KB


/////// Fetch
`define ICACHE_NLINES 4
`define ICACHE_LINE_WIDTH 128
`define ICACHE_BYTEINLINE_WIDTH 4
`define ICACHE_INDEX_WIDTH 2
`define ICACHE_TAG_WIDTH 26


/////// Decode
// Register file
`define REG_FILE_WIDTH 32
`define REG_FILE_NREG  32
`define ADDR_WIDTH      5
`define DATA_WIDTH      5

`endif

Project/Monocycle/alu.v
`include "header.vh"

module alu(
    input [5:0] op,
    input [(`REG_FILE_WIDTH-1):0] x, y,
    output reg [(`REG_FILE_WIDTH-1):0] w,
    output reg  cmp);

initial begin
	w = 32'h0000_0000;
end

always @(*) begin
	cmp <= 0;
	case (op)
        // Arithmetic operations
        5'h00: w <= x + y;      // 0: ADD 
        5'h01: w <= x - y;      // 1: SUB 
    	5'h02: w <= x * y;      // 2: MUL

        // Relational operations
        5'h09: cmp <= (x < y);  // 9: LT
        5'h0A: cmp <= (x > y);  // 10: GT
        5'h0B: cmp <= (x == y); // 11: EQ


        /*

        // Bit-wise operations
        5'h03: w <= x | y;      // 3: OR
        5'h04: w <= x & y;      // 4: AND
        5'h05: w <= x ^ y;      // 5: XOR

        // Shift operations
        5'h06: w <= x << y;     // 6: SLL
        5'h07: w <= x >> y;     // 7: SRL

        // Relational operations
        5'h09: cmp <= (x < y);  // 9: LT
        5'h0A: cmp <= (x > y);  // 10: GT
        5'h0B: cmp <= (x == y); // 11: EQ

        // I think mem stuff (mv, ld, st...) should be somewhere else
        5'h0C: w <= x | 0;      // 8: MV
        //5'b110010: TLBWrite 

        */

		default: 
            begin
                $display("ALU: Operation unknown!");
            end
	endcase
end
endmodule

Project/Monocycle/alu_tb.v
`timescale 1ns/1ns
`include "alu.v"

module alu_tb;
    reg [5:0] op;
    reg [(`REG_FILE_WIDTH-1):0] x, y;
    wire [(`REG_FILE_WIDTH-1):0] w;
    wire cmp;

alu uut(op, x, y, w, cmp);

integer i;
initial begin
    $dumpfile("alu_tb.vcd");
    $dumpvars(0, alu_tb);

    // Give some values to the registers
    x=32'h0000_0001;
    y=32'h0000_0001;

    op=0;
    for (i = 1; i < 13; i=i+1) begin
        #5;
        op = op + 1;
        $display(op);
    end

    x=32'h0000_0010;
    y=32'h0000_00F1;

    op=0;
    for (i = 1; i < 13; i=i+1) begin
        #5;
        op = op + 1;
    end
end

endmodule

Project/Monocycle/alu_tb.vcd
$date
	Wed Jan 19 00:56:18 2022
$end
$version
	Icarus Verilog
$end
$timescale
	1ns
$end
$scope module alu_tb $end
$var wire 1 ! cmp $end
$var wire 32 " w [31:0] $end
$var integer 32 # i [31:0] $end
$var reg 6 $ op [5:0] $end
$var reg 32 % x [31:0] $end
$var reg 32 & y [31:0] $end
$scope module uut $end
$var wire 6 ' op [5:0] $end
$var wire 32 ( x [31:0] $end
$var wire 32 ) y [31:0] $end
$var reg 1 * cmp $end
$var reg 32 + w [31:0] $end
$upscope $end
$upscope $end
$enddefinitions $end
#0
$dumpvars
b10 +
0*
b1 )
b1 (
b0 '
b1 &
b1 %
b0 $
b1 #
b10 "
0!
$end
#5
b0 +
b0 "
b10 #
b1 $
b1 '
#10
b1 +
b1 "
b11 #
b10 $
b10 '
#15
b100 #
b11 $
b11 '
#20
b101 #
b100 $
b100 '
#25
b0 +
b0 "
b110 #
b101 $
b101 '
#30
b10 +
b10 "
b111 #
b110 $
b110 '
#35
b0 +
b0 "
b1000 #
b111 $
b111 '
#40
b1001 #
b1000 $
b1000 '
#45
b1010 #
b1001 $
b1001 '
#50
b1011 #
b1010 $
b1010 '
#55
1*
1!
b1100 #
b1011 $
b1011 '
#60
b100000001 +
b100000001 "
0*
0!
b11110001 &
b11110001 )
b10000 %
b10000 (
b1 #
b0 $
b0 '
#65
b11111111111111111111111100011111 +
b11111111111111111111111100011111 "
b10 #
b1 $
b1 '
#70
b111100010000 +
b111100010000 "
b11 #
b10 $
b10 '
#75
b11110001 +
b11110001 "
b100 #
b11 $
b11 '
#80
b10000 +
b10000 "
b101 #
b100 $
b100 '
#85
b11100001 +
b11100001 "
b110 #
b101 $
b101 '
#90
b0 +
b0 "
b111 #
b110 $
b110 '
#95
b1000 #
b111 $
b111 '
#100
b1001 #
b1000 $
b1000 '
#105
1*
1!
b1010 #
b1001 $
b1001 '
#110
0*
0!
b1011 #
b1010 $
b1010 '
#115
b1100 #
b1011 $
b1011 '
#120
b10000 +
b10000 "
b1101 #
b1100 $
b1100 '
