Project/Monocycle/header.vh
`ifndef Macros_header
`define Macros_header
// Basics
`define BYTE_SIZE       1
`define WORD_SIZE       4

/////////////// Global stuff
// Virtual and Physical memory
`define VIRT_ADDR_WIDTH 32
`define PHY_ADDR_WIDTH  20
`define PAGE_SIZE_BITS  12 // 4 KB
`define CODE_START 4096
`define OS_START 8192
`define MEM_LINE_WIDTH 128

/////// Fetch
`define ICACHE_NLINES 4
`define ICACHE_LINE_WIDTH 128
`define ICACHE_BYTEINLINE_WIDTH 2
`define ICACHE_INDEX_WIDTH 2
`define ICACHE_TAG_WIDTH 28
`define MEM_ADDRESS_LEN 28
`define INST_WIDTH 32


/////// Decode
// Register file
`define REG_FILE_WIDTH 32
`define REG_FILE_NREG  32
`define ADDR_WIDTH      5
`define DATA_WIDTH      5


/////// Memory
// Virtual and Physical memory
`define VIRT_ADDR_WIDTH     32
`define PHY_ADDR_WIDTH      20
`define PAGE_SIZE           12  // 4 KB
`define PHY_PAGE_NUM_WIDTH  `PHY_ADDR_WIDTH - `PAGE_SIZE
`define DCACHE_NLINES 4
`define DCACHE_LINE_WIDTH 128
`define DCACHE_BYTEINLINE_WIDTH 2
`define DCACHE_INDEX_WIDTH 2
`define DCACHE_TAG_WIDTH 28

// Main mamory
`define MEM_DATA_WIDTH  128
`define MEM_DATA_SIZE   32768 // 2^20 = 1048576 // 1MB = 1048576 --> 1048576/32 = 32768

// iTLB
`define ITLB_NUM_LINES  4


/////// Cache
// Store Buffer
`define SB_ADDR_WIDTH 32
`define SB_DATA_WIDTH 32
`define SB_NLINES   4
`define SB_WIDTH  `SB_ADDR_WIDTH + `SB_DATA_WIDTH


`endif

Project/Monocycle/iCache.v
`include "header.vh"

module iCache (
        // SYSTEM
    input clk,
    input wrt_en,
    input reset,


    // Inputs
    input [(`VIRT_ADDR_WIDTH)-1:0] addr, // Address to read (from PC)
    //input [(`ICACHE_LINE_WIDTH-1):0] data_to_fill, // Data to fill in the cache
    //input read_ready_from_mem, // Data requested to mem is ready
    //input written_data_ack, // 

    // Outputs
    output reg [31:0] instr, // Instruction to send to next stage
    output reg cache_hit); // Hit?
    //output reg reqI_mem, // Request inst to memory
    //output reg [25:0] reqAddrI_mem); // Address of the requested address


    /*
    |31          TAG            6|5  Idx  4|3 byte-in-line 0|     
    ---------------------------------------------------------
    */

    // Internal registers
   	reg [(`ICACHE_LINE_WIDTH-1):0] cache_data [(`ICACHE_NLINES-1):0];   // iCache memory
	reg [(`ICACHE_TAG_WIDTH-1):0] cache_tag [(`ICACHE_NLINES-1):0];     // Tag of each line
	reg [(`ICACHE_NLINES-1):0] cache_val_bit;    // Valid bit for each line
    
    // Wires to connect input-output
    wire [(`ICACHE_TAG_WIDTH-1):0] addr_tag;    // Memory tag
    wire [(`ICACHE_INDEX_WIDTH-1):0] addr_index;    // iCache line (direct mapped)
    wire [(`ICACHE_BYTEINLINE_WIDTH-1):0] addr_byte; // Locate the byte-in-line

    // Assign bits from addr (from PC) to tag, line and byteinline
    /*
    integer p_strt, p_end; // pointers
    p_strt = `VIRT_ADDR_WIDTH-1;
    p_end = `VIRT_ADDR_WIDTH - `ICACHE_TAG_WIDTH;
    assign addr_tag = addr[p_strt:p_end];  // 31:6
    p_strt = p_end - 1;
    p_end = p_end - `ICACHE_INDEX_WIDTH;
    assign addr_index = addr[p_strt:p_end]; // 5:4
    p_strt = p_end - 1;
    p_end = p_end - `ICACHE_BYTEINLINE_WIDTH; 
    assign addr_byte = addr[p_strt:p_end];  // 3:0
    */
    assign addr_tag = addr[31:6];
    assign addr_index = addr[5:4];
    assign addr_byte = addr[3:0];
    //reg pending_req;
    //reg req_valid;
    //reg ready_next;

    integer line;
    initial begin
        //pending_req = 1'b0;
        //req_valid = 1'b0;
        //ready_next = 1'b0;
        // Set each line of the iCache as not valid. No need to ctrl the data inside as it'll be overwritten
        for (line=0; line<`ICACHE_NLINES; line=line+1) begin
            cache_data[line] = 0;
            cache_tag[line] = 0;
            cache_val_bit[line] = 1'b0;            
        end

        cache_data[1] = 128'hAAAAAAAA_BBBBBBBB_CCCCCCCC_DDDDDDDD;
        cache_tag[1] = 'b00_00000000_00000000_00000001;
        cache_val_bit[1] = 1'b1;
        
	end

    always @(negedge clk ) begin

        // Flush iCache
        if (reset == 1'b1) begin         
            cache_hit = 1'b0;
            cache_val_bit = 4'b0000; // set all lines to invalid
        end

        line = addr_index;
        // Do we have a TAG hit?
        if (addr_tag == cache_tag[line]) begin
            // Is the chache line valid?
            if (cache_val_bit[line] == 1'b1) begin
                // hit and valid. Read the instruction
                cache_hit=1'b1;
                case(addr_byte)
                    0 : instr = cache_data[line][31:0];
                    1 : instr = cache_data[line][63:32];
                    2 : instr = cache_data[line][95:64];
                    3 : instr = cache_data[line][127:96];
			endcase
            end
        end
        
        else begin // Request to memory
            cache_hit = 1'b0;
        end
    end
    
endmodule

Project/Monocycle/iCache_tb.v
`timescale 1ns/1ns
`include "iCache.v"

module iCache_tb;
    reg clk;
    reg wrt_en;
    reg reset;

    reg [(`VIRT_ADDR_WIDTH)-1:0] addr;
    wire [31:0] instr;
    wire cache_hit;

    // Internal registers
   	reg [(`ICACHE_LINE_WIDTH-1):0] cache_data [(`ICACHE_NLINES-1):0];   // iCache memory
	reg [(`ICACHE_TAG_WIDTH-7):0] cache_tag [(`ICACHE_NLINES-1):0];     // Tag of each line
	reg [(`ICACHE_NLINES-1):0] cache_val_bit;    // Valid bit for each line
    
    // Wires to connect input-output
    wire [(`ICACHE_TAG_WIDTH-1):0] addr_tag;    // Memory tag
    wire [(`ICACHE_INDEX_WIDTH-1):0] addr_index;    // iCache line (direct mapped)
    wire [(`ICACHE_BYTEINLINE_WIDTH-1):0] addr_byte; // Locate the byte-in-line

    iCache uut(clk, wrt_en, reset, addr, instr, cache_hit);

always #5 clk = ~clk;

    initial begin
        clk = 0;
        wrt_en = 0;
        reset = 0;

        $dumpfile("iCache_tb.vcd");
        $dumpvars(0, iCache_tb);

        // Try some addr
        #15;
        addr = 32'hF000_0000; #20;
        addr = 32'h0000_0050; #20;
        addr = 32'h0000_0051; #20;
        addr = 32'h0000_0052; #20;
    
        addr = 32'h000F_0050; #20;
        addr = 32'hFFFF_FFC0; #20;
        addr = 32'h0000_0053; #20;
        addr = 32'h0000_0043; #20;

        reset=1;
        addr = 32'hF000_0000; #20;
        addr = 32'h0000_0050; #20;
        addr = 32'h0000_0051; #20;
        addr = 32'h0000_0052; #20;

        $finish;

        $display("Test OK!");
    end
    
endmodule

Project/Monocycle/iCache_tb.vcd
$date
	Thu Jan 20 18:03:40 2022
$end
$version
	Icarus Verilog
$end
$timescale
	1ns
$end
$scope module iCache_tb $end
$var wire 1 ! cache_hit $end
$var wire 32 " instr [31:0] $end
$var reg 32 # addr [31:0] $end
$var reg 1 $ clk $end
$var reg 1 % reset $end
$var reg 1 & wrt_en $end
$scope module uut $end
$var wire 32 ' addr [31:0] $end
$var wire 4 ( addr_byte [3:0] $end
$var wire 2 ) addr_index [1:0] $end
$var wire 26 * addr_tag [25:0] $end
$var wire 1 + clk $end
$var wire 1 , reset $end
$var wire 1 - wrt_en $end
$var reg 1 . cache_hit $end
$var reg 4 / cache_val_bit [3:0] $end
$var reg 32 0 instr [31:0] $end
$var integer 32 1 line [31:0] $end
$upscope $end
$upscope $end
$enddefinitions $end
#0
$dumpvars
b0xx 1
bx 0
b10 /
0.
0-
0,
0+
bx *
bx )
bx (
bx '
0&
0%
0$
bx #
bx "
0!
$end
#5
1$
1+
#10
0$
0+
#15
b11110000000000000000000000 *
b0 )
b0 (
1$
1+
b11110000000000000000000000000000 #
b11110000000000000000000000000000 '
#20
b0 1
0$
0+
#25
1$
1+
#30
0$
0+
#35
b1 *
b1 )
1$
1+
b1010000 #
b1010000 '
#40
b11011101110111011101110111011101 0
b11011101110111011101110111011101 "
1.
1!
b1 1
0$
0+
#45
1$
1+
#50
0$
0+
#55
b1 (
1$
1+
b1010001 #
b1010001 '
#60
b11001100110011001100110011001100 0
b11001100110011001100110011001100 "
0$
0+
#65
1$
1+
#70
0$
0+
#75
b10 (
1$
1+
b1010010 #
b1010010 '
#80
b10111011101110111011101110111011 0
b10111011101110111011101110111011 "
0$
0+
#85
1$
1+
#90
0$
0+
#95
b11110000000001 *
b0 (
1$
1+
b11110000000001010000 #
b11110000000001010000 '
#100
0.
0!
0$
0+
#105
1$
1+
#110
0$
0+
#115
b11111111111111111111111111 *
b0 )
1$
1+
b11111111111111111111111111000000 #
b11111111111111111111111111000000 '
#120
b0 1
0$
0+
#125
1$
1+
#130
0$
0+
#135
b1 *
b1 )
b11 (
1$
1+
b1010011 #
b1010011 '
#140
b10101010101010101010101010101010 0
b10101010101010101010101010101010 "
1.
1!
b1 1
0$
0+
#145
1$
1+
#150
0$
0+
#155
b0 )
1$
1+
b1000011 #
b1000011 '
#160
0.
0!
b0 1
0$
0+
#165
1$
1+
#170
0$
0+
#175
b11110000000000000000000000 *
b0 (
1$
1+
b11110000000000000000000000000000 #
b11110000000000000000000000000000 '
1%
1,
#180
b0 /
0$
0+
#185
1$
1+
#190
0$
0+
#195
b1 *
b1 )
1$
1+
b1010000 #
b1010000 '
#200
b1 1
0$
0+
#205
1$
1+
#210
0$
0+
#215
b1 (
1$
1+
b1010001 #
b1010001 '
#220
0$
0+
#225
1$
1+
#230
0$
0+
#235
b10 (
1$
1+
b1010010 #
b1010010 '
