Project/Monocycle/header.vh
`ifndef Macros_header
`define Macros_header
// Basics
`define BYTE_SIZE       1
`define WORD_SIZE       4

/////////////// Global stuff
// Virtual and Physical memory
`define VIRT_ADDR_WIDTH 32
`define PHY_ADDR_WIDTH  20
`define PAGE_SIZE_BITS  12 // 4 KB
`define CODE_START 4096
`define OS_START 8192
`define MEM_LINE_WIDTH 128

/////// Fetch
`define ICACHE_NLINES 4
`define ICACHE_LINE_WIDTH 128
`define ICACHE_BYTEINLINE_WIDTH 2
`define ICACHE_INDEX_WIDTH 2
`define ICACHE_TAG_WIDTH 28
`define MEM_ADDRESS_LEN 28
`define INST_WIDTH 32


/////// Decode
// Register file
`define REG_FILE_WIDTH 32
`define REG_FILE_NREG  32
`define ADDR_WIDTH      5
`define DATA_WIDTH      5


/////// Memory
// Virtual and Physical memory
`define VIRT_ADDR_WIDTH     32
`define PHY_ADDR_WIDTH      20
`define PAGE_SIZE           12  // 4 KB
`define PHY_PAGE_NUM_WIDTH  `PHY_ADDR_WIDTH - `PAGE_SIZE
`define DCACHE_NLINES 4
`define DCACHE_LINE_WIDTH 128
`define DCACHE_BYTEINLINE_WIDTH 2
`define DCACHE_INDEX_WIDTH 2
`define DCACHE_TAG_WIDTH 28

// Main mamory
`define MEM_DATA_WIDTH  128
`define MEM_DATA_SIZE   32768 // 2^20 = 1048576 // 1MB = 1048576 --> 1048576/32 = 32768

// iTLB
`define ITLB_NUM_LINES  4


/////// Cache
// Store Buffer
`define SB_ADDR_WIDTH 32
`define SB_DATA_WIDTH 32
`define SB_NLINES   4
`define SB_WIDTH  `SB_ADDR_WIDTH + `SB_DATA_WIDTH


`endif

Project/Monocycle/main_memory.v
`include "header.vh"


module main_memory(    
    // Inputs
    input reset, 
    input [31:0] addr, // TODO: Use Virtual 
    input [(`MEM_DATA_WIDTH-1):0] data_to_write,
    input wrt_en,

    // Outputs
    output reg [(`MEM_DATA_WIDTH-1):0] data_to_read);


    // Internal registers
    reg [31:0] memory [(`MEM_DATA_SIZE)-1:0]; // 2^20
    integer i;

    initial begin
        memory[0] = 32'b0000_1000_0000_0001_0000_0000_1000_0000; // ADDI R1 <- R0,0x80 //128
        memory[1] = 32'b000010_00000_11111_0000_0000_0000_0000; // ADDI R31 <- R0,0x00 //0
        memory[2] = 32'b000010_00000_00101_0000_0000_0000_0000; // ADDI R5 <- R0,0x00 //0 i
        memory[3] = 32'b000010_00000_00010_0000_0000_0000_0000; // ADDI R2 <- R0,0x00 //0 count
        memory[4] = 32'b000100_00010_00011_0010_0000_0000_0000; // LD R3 <- 0x2000(R2)
        memory[5] = 32'b000000_00011_11111_11111_000_0000_0010; // ADD R31 <- R3,R31
        memory[6] = 32'b000010_00000_00010_0000_0000_0000_0100; // ADDI R2 <- R0,0x04 //4 ++count
        memory[7] = 32'b000010_00000_00101_0000_0000_0000_0001; // ADDI R5 <- R0,0x01 //1 ++count
        memory[8] = 32'b000000_00101_00110_0010_1000_0000_1000; // COMPLT R6 <- R5, R1
        memory[9] = 32'b001001_00110_00000_0000_0000_0000_0000;

        for (i = 10; i<`MEM_DATA_SIZE; i=i+1) begin
            memory[i] = 32'b000000_00000_00000_0000_0000_0000_0000;
        end

    end

    always @ (*) begin
        
        if (reset == 1'b1) begin // Restart memory to do the basic operations
            for (i = 0; i<`MEM_DATA_SIZE; i=i+1) begin
                memory[i] = 32'b000000_00000_00000_0000_0000_0000_0000;
            end
        end

        else begin
            // If we enable writting, assume we want to write to memory
            if (wrt_en == 1'b1) begin
               {memory[addr], memory[addr+1], memory[addr+2], memory[addr+3]} = data_to_write;
            end
            // If writting is not enable, assume we want to read from memory
            else begin
                data_to_read = {memory[addr], memory[addr+1], memory[addr+2], memory[addr+3]};
            end
        end

    end

endmodule

Project/Monocycle/main_memory_tb.v
`timescale 1ns/1ns
`include "main_memory.v"

module main_memory_tb;
    // Inputs
    reg reset; 
    reg [31:0] addr; // TODO: Use Virtual 
    reg [(`MEM_DATA_WIDTH-1):0] data_to_write;
    reg wrt_en;

    // Outputs
    wire [(`MEM_DATA_WIDTH-1):0] data_to_read;


    // Internal registers
    reg [31:0] memory [127:0]; // 2^20

    main_memory uut(reset, addr, data_to_write, wrt_en, data_to_read);

    wire [(`MEM_DATA_SIZE-1):0] test_memory;

    assign test_memory = memory[0];

    initial begin
    $dumpfile("main_memory_tb.vcd");
    $dumpvars(0, main_memory_tb);

    // Read some addr
    reset = 0;
    wrt_en = 0;
    addr = 32'h0000_0000; #10;
    $display(data_to_read);
    addr = 32'h0000_0005; #10;
    addr = 32'h0000_0009; #10;
    addr = 32'h0000_000F; #10;
    addr = 32'h0000_0FF5; #10;

    $display("Write some addr");
    // Write some addr
    wrt_en = 1;
    data_to_write = 128'h0000_0000_0000_0000_0000_0000_0000_0000;
    addr = 32'h0000_0000; #10;
    // Overwritte address 0
    data_to_write = 128'h0000_0000_0000_0000_0000_FFFF_FFFF_0000; #30;
    wrt_en = 0; #10;
    
    // Read addr 0
    addr = 32'h0000_0000; #30;

    // Flush memory
    reset = 1; #10;
    reset = 0; #20;

    // Read after flush
    addr = 32'h0000_0000; #30;
    addr = 32'h0000_0005; #30;


    // Write after memory reset
    // Overwritte address 0
    wrt_en=1;
    addr = 32'h0000_0000;
    data_to_write = 128'hFFFF_AAAA_CCCC_EEEE_0000_FFFF_FFFF_1234; #30;
    wrt_en = 0; #30;

    // Read after memory reset

    $display("Test OK!");
end

    
endmodule

Project/Monocycle/main_memory_tb.vcd
$date
	Fri Jan 21 17:03:42 2022
$end
$version
	Icarus Verilog
$end
$timescale
	1ns
$end
$scope module main_memory_tb $end
$var wire 128 ! data_to_read [127:0] $end
$var wire 32768 " test_memory [32767:0] $end
$var reg 32 # addr [31:0] $end
$var reg 128 $ data_to_write [127:0] $end
$var reg 1 % reset $end
$var reg 1 & wrt_en $end
$scope module uut $end
$var wire 32 ' addr [31:0] $end
$var wire 128 ( data_to_write [127:0] $end
$var wire 1 ) reset $end
$var wire 1 * wrt_en $end
$var reg 128 + data_to_read [127:0] $end
$var integer 32 , i [31:0] $end
$upscope $end
$upscope $end
$enddefinitions $end
#0
$dumpvars
b1000000000000000 ,
b1000000000010000000010000000000010000001111100000000000000000000100000000101000000000000000000001000000000100000000000000000 +
0*
0)
bx (
b0 '
0&
0%
bx $
b0 #
b0xxxxxxxxxxxxxxxxxxxxxxxxxxxxxxxx "
b1000000000010000000010000000000010000001111100000000000000000000100000000101000000000000000000001000000000100000000000000000 !
$end
#10
b11111111111100000000010000010000000001000000000000001000000100000000101000000000000000100000000101001100010100000001000 +
b11111111111100000000010000010000000001000000000000001000000100000000101000000000000000100000000101001100010100000001000 !
b101 #
b101 '
#20
b100100110000000000000000000000000000000000000000000000000000000000000000000000000000000000000000000000000000000000000000000000 +
b100100110000000000000000000000000000000000000000000000000000000000000000000000000000000000000000000000000000000000000000000000 !
b1001 #
b1001 '
#30
b0 +
b0 !
b1111 #
b1111 '
#40
b111111110101 #
b111111110101 '
#50
b0 #
b0 '
b0 $
b0 (
1&
1*
#60
b111111111111111111111111111111110000000000000000 $
b111111111111111111111111111111110000000000000000 (
#90
b111111111111111111111111111111110000000000000000 +
b111111111111111111111111111111110000000000000000 !
0&
0*
#130
b1000000000000000 ,
1%
1)
#140
b0 +
b0 !
0%
0)
#190
b101 #
b101 '
#220
b11111111111111111010101010101010110011001100110011101110111011100000000000000000111111111111111111111111111111110001001000110100 $
b11111111111111111010101010101010110011001100110011101110111011100000000000000000111111111111111111111111111111110001001000110100 (
b0 #
b0 '
1&
1*
#250
b11111111111111111010101010101010110011001100110011101110111011100000000000000000111111111111111111111111111111110001001000110100 +
b11111111111111111010101010101010110011001100110011101110111011100000000000000000111111111111111111111111111111110001001000110100 !
0&
0*
