Project/Monocycle/header.vh
`ifndef Macros_header
`define Macros_header
// Basics
`define BYTE_SIZE       1
`define WORD_SIZE       4

/////////////// Global stuff

// Virtual and Physical memory
`define VIRT_ADDR_WIDTH 32
`define PHY_ADDR_WIDTH  20
`define PAGE_SIZE_BITS  12 // 4 KB


/////// Fetch
`define ICACHE_NLINES 4
`define ICACHE_LINE_WIDTH 128
`define ICACHE_BYTEINLINE_WIDTH 4
`define ICACHE_INDEX_WIDTH 2
`define ICACHE_TAG_WIDTH 26


/////// Decode
// Register file
`define REG_FILE_WIDTH 32
`define REG_FILE_NREG  32
`define ADDR_WIDTH      5
`define DATA_WIDTH      5

`endif

Project/regFile.v
`ifndef _regFile
`define _regFile

`include "header.vh"

module regFile(

    // SYSTEM
    input clk,
    input wrt,

    // Inputs
    input [(`ADDR_WIDTH-1):0] addrA,  // Address to read A
    input [(`ADDR_WIDTH-1):0] addrB,  // Address to read B
    input [(`ADDR_WIDTH-1):0] addrD,  // Address to write D
    input [(`REG_FILE_WIDTH-1):0] d,      // Data to write

    // Outputs
    output [(`REG_FILE_WIDTH-1):0] data_a,  // Data from regA
    output [(`REG_FILE_WIDTH-1):0] data_b); // Data from regB


    // Internal registers
    reg [(`REG_FILE_WIDTH-1):0] regFile[(`REG_FILE_NREG-1):0];

	reg [(`ADDR_WIDTH-1):0] addrA_reg;
	reg [(`ADDR_WIDTH-1):0] addrB_reg;
	reg [(`ADDR_WIDTH-1):0] addrD_reg;
    
    integer i;

    initial begin
        for (i=0; i<`REG_FILE_NREG; i=i+1) begin
             regFile[i] = 32'h0000_0000;   
        end
	end


    always @ (posedge clk)
        begin
            if (wrt)
                regFile[addrD_reg] <= d;
        end
        
    always @(negedge clk)
    begin
        addrA_reg <= addrA;
        addrB_reg <= addrB;
        addrD_reg <= addrD;
    end

    assign data_a = regFile[addrA_reg];
    assign data_b = regFile[addrB_reg];

endmodule

`endif

Project/regFile_tb.v
`timescale 1ns/1ns
`include "regFile.v"

module regFile_tb;
    reg clk;
    reg wrt;

    reg [(`ADDR_WIDTH-1):0] addrA;
    reg [(`ADDR_WIDTH-1):0] addrB;
    reg [(`ADDR_WIDTH-1):0] addrD;
    reg [(`REG_FILE_WIDTH-1):0] d;

    wire [(`REG_FILE_WIDTH-1):0] data_a;
    wire [(`REG_FILE_WIDTH-1):0] data_b;

    reg [(`REG_FILE_WIDTH-1):0] regFile[(`REG_FILE_NREG-1):0];

	reg [(`ADDR_WIDTH-1):0] addrA_reg;
	reg [(`ADDR_WIDTH-1):0] addrB_reg;
	reg [(`ADDR_WIDTH-1):0] addrD_reg;

    regFile uut(clk, wrt, addrA, addrB, addrD,
    d, data_a, data_b);

    always #5 clk = ~clk;

    initial begin
        clk = 0;
        wrt = 0;

        $dumpfile("regFile_tb.vcd");
        $dumpvars(0, regFile_tb);

        // Try some addr
        addrA=5'b0001; #5;
        addrB=5'b1111; #10;
        addrA=5'b0010; #5;
        addrD=5'b0110; #15;

        // Try to write to r0 without wrt enabled
        d=32'h0000_4544;
        addrD=5'b0000;
        addrA=5'b0000; #25;

        // Try to write to r0 with wrt enabled
        wrt = 1;
        d=32'h0000_4541;
        addrD=5'b0000;
        addrA=5'b0000; #25;
        wrt = 0;
        
        // Try to read from addrB
        addrB=5'b0000; #15;

        $finish;

        $display("Test OK!");
    end


endmodule

Project/Monocycle/regFile_tb.vcd
$date
	Tue Jan 18 21:03:35 2022
$end
$version
	Icarus Verilog
$end
$timescale
	1ns
$end
$scope module regFile_tb $end
$var wire 32 ! data_a [31:0] $end
$var wire 32 " data_b [31:0] $end
$var reg 5 # addrA [4:0] $end
$var reg 5 $ addrB [4:0] $end
$var reg 5 % addrD [4:0] $end
$var reg 1 & clk $end
$var reg 32 ' d [31:0] $end
$var reg 1 ( wrt $end
$scope module uut $end
$var wire 5 ) addrA [4:0] $end
$var wire 5 * addrB [4:0] $end
$var wire 5 + addrD [4:0] $end
$var wire 1 , clk $end
$var wire 32 - d [31:0] $end
$var wire 32 . data_a [31:0] $end
$var wire 32 / data_b [31:0] $end
$var wire 1 0 wrt $end
$var reg 5 1 addrA_reg [4:0] $end
$var reg 5 2 addrB_reg [4:0] $end
$var reg 5 3 addrD_reg [4:0] $end
$var integer 32 4 i [31:0] $end
$upscope $end
$upscope $end
$enddefinitions $end
#0
$dumpvars
b100000 4
bx 3
bx 2
b1 1
00
bx /
b0 .
bx -
0,
bx +
bx *
b1 )
0(
bx '
0&
bx %
bx $
b1 #
bx "
b0 !
$end
#5
b1111 $
b1111 *
1&
1,
#10
b1111 2
b0 "
b0 /
0&
0,
#15
1&
1,
b10 #
b10 )
#20
b110 3
b10 1
0&
0,
b110 %
b110 +
#25
1&
1,
#30
0&
0,
#35
1&
1,
b0 #
b0 )
b0 %
b0 +
b100010101000100 '
b100010101000100 -
#40
b0 3
b0 1
0&
0,
#45
1&
1,
#50
0&
0,
#55
1&
1,
#60
0&
0,
b100010101000001 '
b100010101000001 -
1(
10
#65
b100010101000001 !
b100010101000001 .
1&
1,
#70
0&
0,
#75
1&
1,
#80
0&
0,
#85
1&
1,
b0 $
b0 *
0(
00
#90
b0 2
b100010101000001 "
b100010101000001 /
0&
0,
