Project/header.vh
`ifndef Macros_header
`define Macros_header
// Basics
`define BYTE_SIZE       1
`define WORD_SIZE       4

/////////////// Global stuff

// Virtual and Physical memory
`define VIRT_ADDR_WIDTH 32
`define PHY_ADDR_WIDTH  20
`define PAGE_SIZE_BITS  12 // 4 KB


// Register file
`define REG_FILE_WIDTH 32
`define REG_FILE_NREG  32
`define ADDR_WIDTH      5
`define DATA_WIDTH      5

`endif

Project/alu.v
`include "header.vh"

module alu(
    input [4:0] op, 
    input [(`REG_FILE_WIDTH-1):0] x, y,
    output reg [(`REG_FILE_WIDTH-1):0] w,
    output reg  cmp);

initial begin
	w = 32'h0000_0000;
end

always @(*) begin
	cmp <= 0;
	case (op)
        // Arithmetic operations
        5'b00000: w <= x + y;      // 0: ADD 
        5'b00001: w <= x - y;      // 1: SUB 
    	5'b00010: w <= x * y;      // 2: MUL

        // Bit-wise operations
        5'b00011: w <= x | y;      // 3: OR
        5'b00100: w <= x & y;      // 4: AND
        5'b00101: w <= x ^ y;      // 5: XOR

        // Shift operations
        5'b00110: w <= x << y;     // 6: SLL
        5'b00111: w <= x >> y;     // 7: SRL

        // Relational operations
        5'b01001: cmp <= (x < y);  // 9: LT
        5'b01010: cmp <= (x > y);  // 10: GT
        5'b01011: cmp <= (x == y); // 11: EQ

        
        5'b01100: w <= x + y;      // 12: JMP TODO!
        5'b01000: w <= x | 0;      // 8: MV
        //5'b110010: TLBWrite 

		default: 
		begin
			$display("ALU: Operation unknown!");
		end
	endcase
end
endmodule

Project/alu_tb.v
`timescale 1ns/1ns
`include "alu.v"

module alu_tb;
    reg [4:0] op;
    reg [(`REG_FILE_WIDTH-1):0] x, y;
    wire [(`REG_FILE_WIDTH-1):0] w;
    wire cmp;

alu uut(op, x, y, w, cmp);

integer i;
initial begin
    $dumpfile("alu_tb.vcd");
    $dumpvars(0, alu_tb);

    // Give some values to the registers
    x=32'h0000_0001;
    y=32'h0000_0001;

    op=5'b00000;
    for (i = 1; i < 13; i=i+1) begin
        #5;
        op = op + 1'b1;
        $display(op);
    end

    x=32'h0000_0010;
    y=32'h0000_00F1;

    op=5'b00000;
    for (i = 1; i < 13; i=i+1) begin
        #10;
        op = op + 5'b00001;
    end
end

endmodule

Project/alu_tb.vcd
$date
	Wed Jan 19 00:07:18 2022
$end
$version
	Icarus Verilog
$end
$timescale
	1ns
$end
$scope module alu_tb $end
$var wire 1 ! cmp $end
$var wire 32 " w [31:0] $end
$var integer 32 # i [31:0] $end
$var reg 5 $ op [4:0] $end
$var reg 32 % x [31:0] $end
$var reg 32 & y [31:0] $end
$scope module uut $end
$var wire 5 ' op [4:0] $end
$var wire 32 ( x [31:0] $end
$var wire 32 ) y [31:0] $end
$var reg 1 * cmp $end
$var reg 32 + w [31:0] $end
$upscope $end
$upscope $end
$enddefinitions $end
#0
$dumpvars
b0 +
0*
b0 )
b0 (
b0 '
b0 &
b0 %
b0 $
b1 #
b0 "
0!
$end
#5
b10 #
b1 $
b1 '
#10
b11 #
b10 $
b10 '
#15
b100 #
b11 $
b11 '
#20
b101 #
b100 $
b100 '
#25
b110 #
b101 $
b101 '
#30
b111 #
b110 $
b110 '
#35
b1000 #
b111 $
b111 '
#40
b1001 #
b1000 $
b1000 '
#45
b1010 #
b1001 $
b1001 '
#50
b1011 #
b1010 $
b1010 '
#55
1*
1!
b1100 #
b1011 $
b1011 '
#60
b100000001 +
b100000001 "
0*
0!
b11110001 &
b11110001 )
b10000 %
b10000 (
b1 #
b0 $
b0 '
#70
b11111111111111111111111100011111 +
b11111111111111111111111100011111 "
b10 #
b1 $
b1 '
#80
b111100010000 +
b111100010000 "
b11 #
b10 $
b10 '
#90
b11110001 +
b11110001 "
b100 #
b11 $
b11 '
#100
b10000 +
b10000 "
b101 #
b100 $
b100 '
#110
b11100001 +
b11100001 "
b110 #
b101 $
b101 '
#120
b0 +
b0 "
b111 #
b110 $
b110 '
#130
b1000 #
b111 $
b111 '
#140
b10000 +
b10000 "
b1001 #
b1000 $
b1000 '
#150
1*
1!
b1010 #
b1001 $
b1001 '
#160
0*
0!
b1011 #
b1010 $
b1010 '
#170
b1100 #
b1011 $
b1011 '
#180
b100000001 +
b100000001 "
b1101 #
b1100 $
b1100 '
